{"1": ["1", "-", "1", null, "POGA\u010cAR Tadej", "22", "UAE Team Emirates", "1000", "500", null, "82:56:36", "..", null], "2": ["2", "-", "18", null, "VINGEGAARD Jonas", "24", "Team Jumbo-Visma", "800", "380", null, "5:20", "..", null], "3": ["3", "-", "22", null, "CARAPAZ Richard", "28", "INEOS Grenadiers", "675", "340", null, "7:03", "..", null], "4": ["4", "-", "124", null, "O'CONNOR Ben", "25", "AG2R Citro\u00ebn Team", "575", "300", null, "10:02", "..", null], "5": ["5", "-", "73", null, "KELDERMAN Wilco", "30", "BORA - hansgrohe", "475", "280", null, "10:13", "..", null], "6": ["6", "-", "65", null, "MAS Enric", "26", "Movistar Team", "400", "260", null, "11:43", "..", null], "7": ["7", "-", "188", null, "LUTSENKO Alexey", "28", "Astana - Premier Tech", "325", "240", null, "12:23", "..", null], "8": ["8", "-", "91", null, "MARTIN Guillaume", "28", "Cofidis", "275", "220", null, "15:33", "..", null], "9": ["9", "-", "162", null, "BILBAO Pello", "31", "Bahrain - Victorious", "225", "210", null, "16:04", "..", null], "10": ["10", "-", "111", null, "UR\u00c1N Rigoberto", "34", "EF Education - Nippo", "175", "200", null, "18:34", "..", null], "11": ["11", "-", "81", null, "GAUDU David", "24", "Groupama - FDJ", "150", "190", null, "21:50", "..", null], "12": ["12", "-", "54", null, "CATTANEO Mattia", "30", "Deceuninck - Quick Step", "125", "180", null, "24:58", "..", null], "13": ["13", "-", "172", null, "CHAVES Esteban", "31", "Team BikeExchange", "105", "170", null, "37:48", "..", null], "14": ["14", "-", "211", null, "MEINTJES Louis", "29", "Intermarch\u00e9 - Wanty - Gobert Mat\u00e9riaux", "85", "160", null, "38:09", "..", null], "15": ["15", "-", "125", null, "PARET-PEINTRE Aur\u00e9lien", "25", "AG2R Citro\u00ebn Team", "75", "150", null, "39:09", "..", null], "16": ["16", "-", "166", null, "POELS Wout", "33", "Bahrain - Victorious", "70", "140", null, "50:35", "..", null], "17": ["17", "-", "167", null, "TEUNS Dylan", "29", "Bahrain - Victorious", "65", "130", null, "51:40", "..", null], "18": ["18", "-", "113", null, "GUERREIRO Ruben", "27", "EF Education - Nippo", "60", "120", null, "54:10", "..", null], "19": ["19", "-", "12", null, "VAN AERT Wout", "26", "Team Jumbo-Visma", "55", "110", null, "57:02", "..", null], "20": ["20", "-", "44", null, "MOLLEMA Bauke", "34", "Trek - Segafredo", "50", "100", null, "1:02:18", "..", null], "21": ["21", "-", "191", null, "HENAO Sergio", "33", "Team Qhubeka NextHash", "40", "95", null, "1:03:12", "..", null], "22": ["22", "-", "223", null, "BONNAMOUR Franck", "26", "B&B Hotels p/b KTM", "40", "90", null, "1:04:35", "..", null], "23": ["24", "&#x25B2;1", "23", null, "CASTROVIEJO Jonathan", "34", "INEOS Grenadiers", "40", "85", null, "1:06:20", "..", null], "24": ["25", "&#x25B2;1", "67", null, "VALVERDE Alejandro", "41", "Movistar Team", "40", "80", null, "1:07:50", "..", null], "25": ["23", "&#x25BC;2", "114", null, "HIGUITA Sergio", "23", "EF Education - Nippo", "40", "75", null, "1:09:16", "..", null], "26": ["26", "-", "187", null, "IZAGIRRE Ion", "32", "Astana - Premier Tech", "30", "70", null, "1:23:39", "..", null], "27": ["27", "-", "74", null, "KONRAD Patrick", "29", "BORA - hansgrohe", "30", "65", null, "1:27:06", "..", null], "28": ["28", "-", "136", null, "QUINTANA Nairo", "31", "Team Ark\u00e9a Samsic", "30", "60", null, "1:33:11", "..", null], "29": ["30", "&#x25B2;1", "104", null, "MEURISSE Xandro", "29", "Alpecin-Fenix", "30", "55", null, "1:40:48", "..", null], "30": ["29", "&#x25BC;1", "51", null, "ALAPHILIPPE Julian", "29", "Deceuninck - Quick Step", "30", "50", null, "1:43:06", "..", null], "31": ["31", "-", "165", null, "MOHORI\u010c Matej", "26", "Bahrain - Victorious", "25", "45", null, "1:50:04", "..", null], "32": ["33", "&#x25B2;1", "15", null, "KUSS Sepp", "26", "Team Jumbo-Visma", "25", "40", null, ",,1:", "..", null], "33": ["32", "&#x25BC;1", "72", null, "BUCHMANN Emanuel", "28", "BORA - hansgrohe", "25", "35", null, "1:51:05", "..", null], "34": ["35", "&#x25B2;1", "7", null, "MAJKA Rafa\u0142", "31", "UAE Team Emirates", "25", "30", null, "1:54:04", "..", null], "35": ["36", "&#x25B2;1", "227", null, "PACHER Quentin", "29", "B&B Hotels p/b KTM", "25", "25", null, "1:55:34", "..", null], "36": ["34", "&#x25BC;2", "43", null, "ELISSONDE Kenny", "29", "Trek - Segafredo", "25", "25", null, "1:56:33", "..", null], "37": ["37", "-", "42", null, "BERNARD Julien", "29", "Trek - Segafredo", "25", "25", null, "2:03:32", "..", null], "38": ["39", "&#x25B2;1", "26", null, "PORTE Richie", "36", "INEOS Grenadiers", "25", "25", null, "2:06:39", "..", null], "39": ["40", "&#x25B2;1", "47", null, "STUYVEN Jasper", "29", "Trek - Segafredo", "25", "25", null, "2:07:39", "..", null], "40": ["41", "&#x25B2;1", "36", null, "MARTIN Dan", "34", "Israel Start-Up Nation", "25", "25", null, "2:09:35", "..", null], "41": ["42", "&#x25B2;1", "21", null, "THOMAS Geraint", "35", "INEOS Grenadiers", "20", "25", null, "2:11:37", "..", null], "42": ["43", "&#x25B2;1", "87", null, "MADOUAS Valentin", "25", "Groupama - FDJ", "20", "25", null, "2:11:39", "..", null], "43": ["44", "&#x25B2;1", "117", null, "POWLESS Neilson", "24", "EF Education - Nippo", "20", "25", null, "2:13:33", "..", null], "44": ["46", "&#x25B2;2", "4", null, "FORMOLO Davide", "28", "UAE Team Emirates", "20", "25", null, "2:15:56", "..", null], "45": ["45", "-", "144", null, "DONOVAN Mark", "22", "Team DSM", "20", "25", null, "2:17:40", "..", null], "46": ["47", "&#x25B2;1", "206", null, "RODR\u00cdGUEZ Cristi\u00e1n", "26", "TotalEnergies", "20", "25", null, "2:19:31", "..", null], "47": ["48", "&#x25B2;1", "201", null, "LATOUR Pierre", "27", "TotalEnergies", "20", "25", null, "2:19:36", "..", null], "48": ["49", "&#x25B2;1", "212", null, "BAKELANTS Jan", "35", "Intermarch\u00e9 - Wanty - Gobert Mat\u00e9riaux", "20", "25", null, "2:21:30", "..", null], "49": ["50", "&#x25B2;1", "86", null, "K\u00dcNG Stefan", "27", "Groupama - FDJ", "20", "25", null, "2:22:03", "..", null], "50": ["52", "&#x25B2;2", "76", null, "POLITT Nils", "27", "BORA - hansgrohe", "20", "25", null, "2:22:44", "..", null], "51": ["53", "&#x25B2;2", "228", null, "ROLLAND Pierre", "34", "B&B Hotels p/b KTM", "15", "25", null, "2:23:11", "..", null], "52": ["54", "&#x25B2;2", "163", null, "COLBRELLI Sonny", "31", "Bahrain - Victorious", "15", "25", null, "2:24:39", "..", null], "53": ["51", "&#x25BC;2", "115", null, "VALGREN Michael", "29", "EF Education - Nippo", "15", "25", null, "2:26:16", "..", null], "54": ["55", "&#x25B2;1", "28", null, "VAN BAARLE Dylan", "29", "INEOS Grenadiers", "15", "25", null, "2:27:07", "..", null], "55": ["56", "&#x25B2;1", "118", null, "RUTSCH Jonas", "23", "EF Education - Nippo", "15", "25", null, "2:29:33", "..", null], "56": ["58", "&#x25B2;2", "116", null, "CORT Magnus", "28", "EF Education - Nippo", "10", "25", null, "2:30:23", "..", null], "57": ["57", "-", "184", null, "FRAILE Omar", "31", "Astana - Premier Tech", "10", "25", null, "2:31:14", "..", null], "58": ["59", "&#x25B2;1", "127", null, "SCH\u00c4R Michael", "34", "AG2R Citro\u00ebn Team", "10", "25", null, "2:35:18", "..", null], "59": ["60", "&#x25B2;1", "102", null, "DILLIER Silvan", "30", "Alpecin-Fenix", "10", "25", null, "2:35:43", "..", null], "60": ["61", "&#x25B2;1", "24", null, "GEOGHEGAN HART Tao", "26", "INEOS Grenadiers", "10", "25", null, "2:37:02", "..", null], "61": ["63", "&#x25B2;2", "134", null, "GESBERT \u00c9lie", "26", "Team Ark\u00e9a Samsic", null, "25", null, "2:38:28", "..", null], "62": ["62", "-", "93", null, "GESCHKE Simon", "35", "Cofidis", null, "25", null, "2:38:51", "..", null], "63": ["64", "&#x25B2;1", "214", null, "ROTA Lorenzo", "26", "Intermarch\u00e9 - Wanty - Gobert Mat\u00e9riaux", null, "25", null, "2:39:57", "..", null], "64": ["67", "&#x25B2;3", "52", null, "ASGREEN Kasper", "26", "Deceuninck - Quick Step", null, "25", null, "2:43:41", "..", null], "65": ["66", "&#x25B2;1", "158", null, "VAN MOER Brent", "23", "Lotto Soudal", null, "25", null, "2:43:49", "..", null], "66": ["65", "&#x25BC;1", "186", null, "HOULE Hugo", "30", "Astana - Premier Tech", null, "25", null, "2:44:39", "..", null], "67": ["70", "&#x25B2;3", "63", null, "ERVITI Imanol", "37", "Movistar Team", null, "25", null, "2:49:07", "..", null], "68": ["69", "&#x25B2;1", "25", null, "KWIATKOWSKI Micha\u0142", "31", "INEOS Grenadiers", null, "25", null, "2:49:22", "..", null], "69": ["71", "&#x25B2;2", "8", null, "MCNULTY Brandon", "23", "UAE Team Emirates", null, "25", null, "2:50:53", "..", null], "70": ["72", "&#x25B2;2", "123", null, "NAESEN Oliver", "30", "AG2R Citro\u00ebn Team", null, "25", null, "2:52:25", "..", null], "71": ["73", "&#x25B2;2", "46", null, "SKUJI\u0145\u0160 Toms", "30", "Trek - Segafredo", null, "25", null, "2:52:56", "..", null], "72": ["74", "&#x25B2;2", "204", null, "DE LA PARTE V\u00edctor", "35", "TotalEnergies", null, "25", null, "2:54:28", "..", null], "73": ["68", "&#x25BC;5", "208", null, "TURGIS Anthony", "27", "TotalEnergies", null, "25", null, "2:55:51", "..", null], "74": ["75", "&#x25B2;1", "182", null, "ARANBURU Alex", "25", "Astana - Premier Tech", null, "25", null, "2:56:44", "..", null], "75": ["76", "&#x25B2;1", "122", null, "GODON Dorian", "25", "AG2R Citro\u00ebn Team", null, "25", null, "2:57:11", "..", null], "76": ["77", "&#x25B2;1", "17", null, "TEUNISSEN Mike", "28", "Team Jumbo-Visma", null, "25", null, "2:58:25", "..", null], "77": ["78", "&#x25B2;1", "3", null, "COSTA Rui", "34", "UAE Team Emirates", null, "25", null, "2:58:29", "..", null], "78": ["79", "&#x25B2;1", "205", null, "DOUBEY Fabien", "27", "TotalEnergies", null, "25", null, "3:02:45", "..", null], "79": ["80", "&#x25B2;1", "171", null, "MATTHEWS Michael", "30", "Team BikeExchange", null, "25", null, "3:03:30", "..", null], "80": ["81", "&#x25B2;1", "218", null, "ZIMMERMANN Georg", "23", "Intermarch\u00e9 - Wanty - Gobert Mat\u00e9riaux", null, "25", null, "3:05:48", "..", null], "81": ["84", "&#x25B2;3", "225", null, "GAUTIER Cyril", "33", "B&B Hotels p/b KTM", null, "25", null, "3:08:30", "..", null], "82": ["82", "-", "153", null, "DE GENDT Thomas", "34", "Lotto Soudal", null, "25", null, "3:08:46", "..", null], "83": ["86", "&#x25B2;3", "82", null, "ARMIRAIL Bruno", "27", "Groupama - FDJ", null, "25", null, "3:09:58", "..", null], "84": ["87", "&#x25B2;3", "92", null, "FERN\u00c1NDEZ Rub\u00e9n", "30", "Cofidis", null, "25", null, "3:10:43", "..", null], "85": ["83", "&#x25BC;2", "156", null, "SWEENY Harry", "23", "Lotto Soudal", null, "25", null, "3:10:52", "..", null], "86": ["88", "&#x25B2;2", "96", null, "PEREZ Anthony", "30", "Cofidis", null, "25", null, "3:10:56", "..", null], "87": ["85", "&#x25BC;2", "94", null, "HERRADA Jes\u00fas", "30", "Cofidis", null, "25", null, "3:11:15", "..", null], "88": ["89", "&#x25B2;1", "222", null, "BARTHE Cyril", "25", "B&B Hotels p/b KTM", null, "25", null, "3:12:31", "..", null], "89": ["90", "&#x25B2;1", "138", null, "SWIFT Connor", "25", "Team Ark\u00e9a Samsic", null, "25", null, "3:13:48", "..", null], "90": ["91", "&#x25B2;1", "62", null, "ARCAS Jorge", "29", "Movistar Team", null, "25", null, "3:14:41", "..", null], "91": ["92", "&#x25B2;1", "95", null, "LAPORTE Christophe", "28", "Cofidis", null, "25", null, "3:15:03", "..", null], "92": ["93", "&#x25B2;1", "97", null, "P\u00c9RICHON Pierre-Luc", "34", "Cofidis", null, "25", null, "3:16:27", "..", null], "93": ["94", "&#x25B2;1", "224", null, "CHEVALIER Maxime", "22", "B&B Hotels p/b KTM", null, "25", null, "3:16:54", "..", null], "94": ["95", "&#x25B2;1", "64", null, "GARC\u00cdA CORTINA Iv\u00e1n", "25", "Movistar Team", null, "25", null, "3:21:25", "..", null], "95": ["96", "&#x25B2;1", "106", null, "RICKAERT Jonas", "27", "Alpecin-Fenix", null, "25", null, "3:22:36", "..", null], "96": ["97", "&#x25B2;1", "168", null, "WRIGHT Fred", "22", "Bahrain - Victorious", null, "25", null, "3:24:19", "..", null], "97": ["98", "&#x25B2;1", "128", null, "VAN AVERMAET Greg", "36", "AG2R Citro\u00ebn Team", null, "25", null, "3:24:29", "..", null], "98": ["99", "&#x25B2;1", "5", null, "HIRSCHI Marc", "22", "UAE Team Emirates", null, "25", null, "3:24:38", "..", null], "99": ["101", "&#x25B2;2", "154", null, "GILBERT Philippe", "39", "Lotto Soudal", null, "25", null, "3:27:22", "..", null], "100": ["102", "&#x25B2;2", "173", null, "DURBRIDGE Luke", "30", "Team BikeExchange", null, "25", null, "3:28:05", "..", null], "101": ["100", "&#x25BC;1", "68", null, "VERONA Carlos", "28", "Movistar Team", null, "25", null, "3:28:40", "..", null], "102": ["103", "&#x25B2;1", "177", null, "MEZGEC Luka", "33", "Team BikeExchange", null, "25", null, "3:30:17", "..", null], "103": ["104", "&#x25B2;1", "112", null, "BISSEGGER Stefan", "22", "EF Education - Nippo", null, "25", null, "3:31:35", "..", null], "104": ["105", "&#x25B2;1", "48", null, "THEUNS Edward", "30", "Trek - Segafredo", null, "25", null, "3:33:31", "..", null], "105": ["107", "&#x25B2;2", "32", null, "BOIVIN Guillaume", "32", "Israel Start-Up Nation", null, "25", null, "3:33:42", "..", null], "106": ["108", "&#x25B2;2", "107", null, "SBARAGLI Kristian", "31", "Alpecin-Fenix", null, "25", null, "3:34:19", "..", null], "107": ["106", "&#x25BC;1", "121", null, "COSNEFROY Beno\u00eet", "25", "AG2R Citro\u00ebn Team", null, "25", null, "3:34:54", "..", null], "108": ["109", "&#x25B2;1", "53", null, "BALLERINI Davide", "26", "Deceuninck - Quick Step", null, "25", null, "3:35:13", "..", null], "109": ["111", "&#x25B2;2", "105", null, "PHILIPSEN Jasper", "23", "Alpecin-Fenix", null, "25", null, "3:42:11", "..", null], "110": ["112", "&#x25B2;2", "2", null, "BJERG Mikkel", "22", "UAE Team Emirates", null, "25", null, "3:42:21", "..", null], "111": ["110", "&#x25BC;1", "147", null, "PEDERSEN Casper", "25", "Team DSM", null, "25", null, "3:42:52", "..", null], "112": ["114", "&#x25B2;2", "6", null, "LAENGEN Vegard Stake", "32", "UAE Team Emirates", null, "25", null, "3:43:33", "..", null], "113": ["115", "&#x25B2;2", "185", null, "GRUZDEV Dmitriy", "35", "Astana - Premier Tech", null, "25", null, "3:44:49", "..", null], "114": ["113", "&#x25BC;1", "176", null, "JUUL-JENSEN Christopher", "32", "Team BikeExchange", null, "25", null, "3:45:07", "..", null], "115": ["116", "&#x25B2;1", "75", null, "OSS Daniel", "34", "BORA - hansgrohe", null, "25", null, "3:46:53", "..", null], "116": ["117", "&#x25B2;1", "77", null, "P\u00d6STLBERGER Lukas", "29", "BORA - hansgrohe", null, "25", null, "3:47:12", "..", null], "117": ["120", "&#x25B2;3", "215", null, "VAN POPPEL Boy", "33", "Intermarch\u00e9 - Wanty - Gobert Mat\u00e9riaux", null, "25", null, "3:50:25", "..", null], "118": ["118", "-", "108", null, "VAKO\u010c Petr", "29", "Alpecin-Fenix", null, "25", null, "3:51:06", "..", null], "119": ["119", "-", "78", null, "SCHELLING Ide", "23", "BORA - hansgrohe", null, "25", null, "3:51:16", "..", null], "120": ["121", "&#x25B2;1", "216", null, "VAN POPPEL Danny", "27", "Intermarch\u00e9 - Wanty - Gobert Mat\u00e9riaux", null, "25", null, "3:52:53", "..", null], "121": ["122", "&#x25B2;1", "198", null, "WALSCHEID Max", "28", "Team Qhubeka NextHash", null, "25", null, "3:53:05", "..", null], "122": ["124", "&#x25B2;2", "33", null, "GOLDSTEIN Omer", "24", "Israel Start-Up Nation", null, "25", null, "3:55:26", "..", null], "123": ["123", "-", "195", null, "CLARKE Simon", "35", "Team Qhubeka NextHash", null, "25", null, "3:56:08", "..", null], "124": ["125", "&#x25B2;1", "192", null, "BARBERO Carlos", "30", "Team Qhubeka NextHash", null, "25", null, "4:00:20", "..", null], "125": ["126", "&#x25B2;1", "34", null, "GREIPEL Andr\u00e9", "39", "Israel Start-Up Nation", null, "25", null, "4:01:26", "..", null], "126": ["128", "&#x25B2;2", "145", null, "EEKHOFF Nils", "23", "Team DSM", null, "25", null, "4:02:44", "..", null], "127": ["129", "&#x25B2;2", "164", null, "HALLER Marco", "30", "Bahrain - Victorious", null, "25", null, "4:03:01", "..", null], "128": ["127", "&#x25BC;1", "146", null, "NIEUWENHUIS Joris", "25", "Team DSM", null, "25", null, "4:03:22", "..", null], "129": ["130", "&#x25B2;1", "207", null, "SIMON Julien", "35", "TotalEnergies", null, "25", null, "4:05:49", "..", null], "130": ["131", "&#x25B2;1", "193", null, "BENNETT Sean", "25", "Team Qhubeka NextHash", null, "25", null, "4:07:42", "..", null], "131": ["133", "&#x25B2;2", "98", null, "WALLAYS Jelle", "32", "Cofidis", null, "25", null, "4:09:46", "..", null], "132": ["132", "-", "203", null, "CABOT J\u00e9r\u00e9my", "29", "TotalEnergies", null, "25", null, "4:11:35", "..", null], "133": ["134", "&#x25B2;1", "31", null, "FROOME Chris", "36", "Israel Start-Up Nation", null, "25", null, "4:12:01", "..", null], "134": ["135", "&#x25B2;1", "38", null, "ZABEL Rick", "27", "Israel Start-Up Nation", null, "25", null, "4:13:07", "..", null], "135": ["136", "&#x25B2;1", "57", null, "DEVENYNS Dries", "37", "Deceuninck - Quick Step", null, "25", null, "4:20:49", "..", null], "136": ["137", "&#x25B2;1", "35", null, "HOLLENSTEIN Reto", "35", "Israel Start-Up Nation", null, "25", null, "4:24:19", "..", null], "137": ["138", "&#x25B2;1", "45", null, "PEDERSEN Mads", "25", "Trek - Segafredo", null, "25", null, "4:29:17", "..", null], "138": ["139", "&#x25B2;1", "58", null, "M\u00d8RK\u00d8V Michael", "36", "Deceuninck - Quick Step", null, "25", null, "4:32:45", "..", null], "139": ["140", "&#x25B2;1", "55", null, "CAVENDISH Mark", "36", "Deceuninck - Quick Step", null, "25", null, "4:34:14", "..", null], "140": ["141", "&#x25B2;1", "143", null, "BOL Cees", "25", "Team DSM", null, "25", null, "4:36:39", "..", null], "141": ["142", "&#x25B2;1", "56", null, "DECLERCQ Tim", "32", "Deceuninck - Quick Step", null, "25", null, "5:01:09", "..", null]}